serverless_flask/__init__.py
serverless_flask/interceptor.py
serverless_flask-0.0.8.dist-info/METADATA
serverless_flask-0.0.8.dist-info/WHEEL
serverless_flask-0.0.8.dist-info/top_level.txt
serverless_flask-0.0.8.dist-info/RECORD
