Metadata-Version: 2.1
Name: serverless-flask
Version: 0.0.8
Summary: add links to readme
Home-page: https://github.com/Queue-inc/serverless-flask
Author: shibatanaoto
Author-email: shibata@queue-inc.com
License: MIT
Keywords: flask,restful,interceptor,AOP
Platform: UNKNOWN
Classifier: Framework :: Flask
Classifier: Programming Language :: Python
Requires-Dist: requests (>=2.18.0)
